<?xml version="1.0" encoding="UTF-8"?>
<configuration scan="true" scanPeriod="30 seconds" debug="false">
    <property name="LOG_HOME" value="./logs"/>

    <appender name="CONSOLE" class="ch.qos.logback.core.ConsoleAppender">
        <encoder class="ch.qos.logback.classic.encoder.PatternLayoutEncoder">
            <pattern>%d{yyyy-MM-dd HH:mm:ss} [%thread] %-5level %logger{50}.%M\(%line\) - %msg%n</pattern>
            <charset>UTF-8</charset>
        </encoder>
    </appender>

    <appender name="FILE" class="ch.qos.logback.core.rolling.RollingFileAppender">
        <!-- 正在写入的日志文件 -->
        <file>${LOG_HOME}/app.log</file>
        <!-- 滚动策略：基于时间和文件大小 -->
        <rollingPolicy class="ch.qos.logback.core.rolling.SizeAndTimeBasedRollingPolicy">
            <fileNamePattern>${LOG_HOME}/app.%d{yyyy-MM-dd}.%i.log.gz</fileNamePattern>
            <maxFileSize>100KB</maxFileSize>
            <maxHistory>30</maxHistory>
            <totalSizeCap>10MB</totalSizeCap>
        </rollingPolicy>
        <encoder>
            <pattern>%d{yyyy-MM-dd HH:mm:ss} [%thread] %-5level %logger{50}.%M\(%line\) - %msg%n</pattern>
            <charset>UTF-8</charset>
        </encoder>
    </appender>

    <appender name="ASYNC_FILE" class="ch.qos.logback.classic.AsyncAppender">
        <discardingThreshold>0</discardingThreshold>
        <queueSize>512</queueSize>
        <appender-ref ref="FILE"/>
    </appender>

    <!-- 异步控制台 appender（可选，开发时一般不需要异步） -->
    <!-- <appender hint="ASYNC_CONSOLE" class="ch.qos.logback.classic.AsyncAppender">
        <queueSize>512</queueSize>
        <appender-ref ref="CONSOLE"/>
    </appender> -->

    <!-- 开发环境：打印 DEBUG 及以上日志到控制台，并异步写入文件 -->
    <springProfile name="dev">
        <root level="DEBUG">
            <appender-ref ref="CONSOLE"/>
            <appender-ref ref="ASYNC_FILE"/>
        </root>
    </springProfile>

    <!-- 生产环境：只打印 INFO 及以上日志到控制台（一般生产不建议开启控制台，但为了容器化方便可以保留），异步写入文件 -->
    <springProfile name="prod">
        <root level="INFO">
            <!-- 生产环境可关闭控制台输出，或仅输出错误级别到控制台 -->
            <appender-ref ref="CONSOLE"/>
            <appender-ref ref="ASYNC_FILE"/>
        </root>
    </springProfile>

    <!-- 默认配置（如果未激活 springProfile，则使用此配置） -->
    <root level="INFO">
        <appender-ref ref="CONSOLE"/>
        <appender-ref ref="ASYNC_FILE"/>
    </root>

    <logger name="org.harvey.vie.theory" level="TRACE"/>

</configuration>